{
    "componentFilePath": "../resources/component/TMFC003-ProductOrderDeliveryOrchestrationAndManagement.yaml",
    "companyName": "",
    "componentName": "TMFC003-ProductOrderDeliveryOrchestrationAndManagement",
    "productName": "",
    "componentUrl": "",
    "productUrl": "",
    "ctkConfig": {},
    "headers": {
        "Accept": "application/json",
        "Content-Type": "application/json"
    },
    "goldenComponentFilePath": "../resources/golden-components/TMFC003-ProductOrderDeliveryOrchestrationAndManagement.yaml",
    "payloads": {
        "TMF669_v4.0.0": {
            "PartyRole": {
                "POST": {
                    "payload": {
                        "name": "qqymucymyd"
                    }
                }
            }
        }
    }
}